{"id": 364, "locationCode": "D-064", "completedCounts": [{"totalAmount": 480, "contents": [{"barcode": "57042756299", "amount": 10}, {"barcode": "67889712417", "amount": 6}, {"barcode": "30886008628", "amount": 10}, {"barcode": "32815928430", "amount": 10}, {"barcode": "34049968552", "amount": 8}, {"barcode": "28957183797", "amount": 9}, {"barcode": "90657989463", "amount": 7}, {"barcode": "93820576297", "amount": 3}, {"barcode": "31523689940", "amount": 5}, {"barcode": "19431937228", "amount": 9}, {"barcode": "90570716299", "amount": 7}, {"barcode": "73503364728", "amount": 9}, {"barcode": "98473408500", "amount": 2}, {"barcode": "73036429454", "amount": 8}, {"barcode": "67780099729", "amount": 7}, {"barcode": "50433537571", "amount": 8}, {"barcode": "31850047425", "amount": 4}, {"barcode": "80997403070", "amount": 4}, {"barcode": "61698614898", "amount": 2}, {"barcode": "52110669143", "amount": 6}, {"barcode": "17247455802", "amount": 1}, {"barcode": "46821686565", "amount": 10}, {"barcode": "57340173080", "amount": 9}, {"barcode": "76397940448", "amount": 1}, {"barcode": "99803961552", "amount": 10}, {"barcode": "48139997022", "amount": 2}, {"barcode": "53594688531", "amount": 10}, {"barcode": "34523855791", "amount": 5}, {"barcode": "44139904450", "amount": 10}, {"barcode": "53983908039", "amount": 1}, {"barcode": "92318660142", "amount": 5}, {"barcode": "37596096644", "amount": 3}, {"barcode": "23154816745", "amount": 6}, {"barcode": "92072758142", "amount": 3}, {"barcode": "15311282623", "amount": 9}, {"barcode": "71131395632", "amount": 1}, {"barcode": "82123716564", "amount": 5}, {"barcode": "96981400445", "amount": 7}, {"barcode": "88145406696", "amount": 3}, {"barcode": "48641230411", "amount": 5}, {"barcode": "92313908410", "amount": 6}, {"barcode": "92024961042", "amount": 5}, {"barcode": "64749265804", "amount": 6}, {"barcode": "84491974328", "amount": 7}, {"barcode": "58954974692", "amount": 8}, {"barcode": "34774857531", "amount": 3}, {"barcode": "98069559643", "amount": 7}, {"barcode": "32240279745", "amount": 4}, {"barcode": "62224207569", "amount": 5}, {"barcode": "80238297532", "amount": 2}, {"barcode": "13716653535", "amount": 1}, {"barcode": "27866941596", "amount": 5}, {"barcode": "66443762439", "amount": 1}, {"barcode": "36433294045", "amount": 6}, {"barcode": "58614288265", "amount": 9}, {"barcode": "25285410405", "amount": 4}, {"barcode": "63401899360", "amount": 7}, {"barcode": "93092343176", "amount": 9}, {"barcode": "46417463138", "amount": 9}, {"barcode": "97702727213", "amount": 1}, {"barcode": "94891187327", "amount": 7}, {"barcode": "82111728224", "amount": 8}, {"barcode": "34950675493", "amount": 8}, {"barcode": "22589992947", "amount": 7}, {"barcode": "94019033556", "amount": 2}, {"barcode": "76973754155", "amount": 3}, {"barcode": "50224820273", "amount": 2}, {"barcode": "54276374645", "amount": 1}, {"barcode": "70052863837", "amount": 2}, {"barcode": "36992496329", "amount": 1}, {"barcode": "42140077771", "amount": 1}, {"barcode": "77185597303", "amount": 7}, {"barcode": "39437827769", "amount": 4}, {"barcode": "41737852346", "amount": 2}, {"barcode": "74063085987", "amount": 2}, {"barcode": "67182645863", "amount": 8}, {"barcode": "19063684592", "amount": 3}, {"barcode": "63983199570", "amount": 10}, {"barcode": "81356690046", "amount": 4}, {"barcode": "46822505805", "amount": 1}, {"barcode": "33517626192", "amount": 8}, {"barcode": "10591847069", "amount": 10}, {"barcode": "24714779076", "amount": 10}, {"barcode": "30358121737", "amount": 5}, {"barcode": "71090955380", "amount": 2}, {"barcode": "68522763905", "amount": 2}, {"barcode": "47696308713", "amount": 3}, {"barcode": "67240642031", "amount": 6}, {"barcode": "21802042736", "amount": 1}, {"barcode": "41822190741", "amount": 5}]}]}