{"id": 311, "locationCode": "D-011", "completedCounts": [{"totalAmount": 332, "contents": [{"barcode": "87334878136", "amount": 10}, {"barcode": "86280047314", "amount": 1}, {"barcode": "86996022674", "amount": 7}, {"barcode": "91433001332", "amount": 9}, {"barcode": "11241098527", "amount": 8}, {"barcode": "66450864998", "amount": 4}, {"barcode": "72741175650", "amount": 1}, {"barcode": "68364636987", "amount": 6}, {"barcode": "47022229671", "amount": 5}, {"barcode": "19418693909", "amount": 7}, {"barcode": "47510972565", "amount": 2}, {"barcode": "33180540577", "amount": 3}, {"barcode": "68137531815", "amount": 8}, {"barcode": "30781778474", "amount": 2}, {"barcode": "59174668433", "amount": 1}, {"barcode": "10675154104", "amount": 3}, {"barcode": "46516646073", "amount": 6}, {"barcode": "91949759010", "amount": 8}, {"barcode": "79737488279", "amount": 9}, {"barcode": "39656518698", "amount": 1}, {"barcode": "70052863837", "amount": 3}, {"barcode": "87685753919", "amount": 9}, {"barcode": "30869848608", "amount": 4}, {"barcode": "54312043358", "amount": 10}, {"barcode": "20888758742", "amount": 5}, {"barcode": "89102542199", "amount": 4}, {"barcode": "56511329081", "amount": 8}, {"barcode": "59920279798", "amount": 3}, {"barcode": "74854925356", "amount": 6}, {"barcode": "13099544288", "amount": 1}, {"barcode": "33862726050", "amount": 5}, {"barcode": "56695207409", "amount": 7}, {"barcode": "20311689747", "amount": 5}, {"barcode": "76819969433", "amount": 5}, {"barcode": "13913694855", "amount": 9}, {"barcode": "70120632307", "amount": 4}, {"barcode": "99803325827", "amount": 5}, {"barcode": "97387812670", "amount": 5}, {"barcode": "16222350276", "amount": 3}, {"barcode": "38581342421", "amount": 8}, {"barcode": "41431124319", "amount": 4}, {"barcode": "64410955056", "amount": 7}, {"barcode": "76763137829", "amount": 7}, {"barcode": "59320044274", "amount": 1}, {"barcode": "74389536842", "amount": 10}, {"barcode": "51876349480", "amount": 8}, {"barcode": "21549913438", "amount": 3}, {"barcode": "71845377109", "amount": 1}, {"barcode": "85326782339", "amount": 3}, {"barcode": "66700945086", "amount": 8}, {"barcode": "11289492020", "amount": 5}, {"barcode": "73390340591", "amount": 8}, {"barcode": "12319620083", "amount": 5}, {"barcode": "50669886592", "amount": 1}, {"barcode": "99515681317", "amount": 7}, {"barcode": "41115858990", "amount": 4}, {"barcode": "59636030891", "amount": 6}, {"barcode": "41658635726", "amount": 1}, {"barcode": "38871785849", "amount": 3}, {"barcode": "13579750909", "amount": 9}, {"barcode": "67803868715", "amount": 5}, {"barcode": "23898132192", "amount": 2}, {"barcode": "17567060895", "amount": 10}, {"barcode": "39873391754", "amount": 4}]}]}