{"id": 110, "locationCode": "B-010", "completedCounts": [{"totalAmount": 462, "contents": [{"barcode": "84841439226", "amount": 3}, {"barcode": "23404721461", "amount": 5}, {"barcode": "43570896934", "amount": 1}, {"barcode": "25176202645", "amount": 4}, {"barcode": "12729643841", "amount": 2}, {"barcode": "85827989225", "amount": 2}, {"barcode": "15368968202", "amount": 4}, {"barcode": "85211223386", "amount": 7}, {"barcode": "46654482693", "amount": 2}, {"barcode": "81608182479", "amount": 1}, {"barcode": "54368571276", "amount": 3}, {"barcode": "38559013511", "amount": 9}, {"barcode": "60284455705", "amount": 4}, {"barcode": "73113423560", "amount": 6}, {"barcode": "14710053174", "amount": 7}, {"barcode": "24359957247", "amount": 5}, {"barcode": "78336904634", "amount": 2}, {"barcode": "57028601280", "amount": 7}, {"barcode": "68691920976", "amount": 3}, {"barcode": "17112700777", "amount": 2}, {"barcode": "61263619662", "amount": 9}, {"barcode": "59438114349", "amount": 4}, {"barcode": "21094759005", "amount": 1}, {"barcode": "56952537356", "amount": 9}, {"barcode": "24091963800", "amount": 6}, {"barcode": "24569580598", "amount": 10}, {"barcode": "73271027094", "amount": 1}, {"barcode": "22366919940", "amount": 7}, {"barcode": "61240458620", "amount": 3}, {"barcode": "60055551990", "amount": 2}, {"barcode": "22349546394", "amount": 4}, {"barcode": "66657401746", "amount": 5}, {"barcode": "52265964138", "amount": 4}, {"barcode": "14692367451", "amount": 2}, {"barcode": "78485806322", "amount": 4}, {"barcode": "51911118370", "amount": 7}, {"barcode": "14327109886", "amount": 6}, {"barcode": "17282387127", "amount": 5}, {"barcode": "20541059595", "amount": 4}, {"barcode": "67728447391", "amount": 6}, {"barcode": "90174028737", "amount": 1}, {"barcode": "47578927052", "amount": 9}, {"barcode": "85055188797", "amount": 7}, {"barcode": "13522128307", "amount": 10}, {"barcode": "49701781985", "amount": 1}, {"barcode": "58856134441", "amount": 3}, {"barcode": "61760839612", "amount": 10}, {"barcode": "81498117197", "amount": 3}, {"barcode": "67517854762", "amount": 9}, {"barcode": "90742068768", "amount": 5}, {"barcode": "20735608964", "amount": 3}, {"barcode": "60761177851", "amount": 3}, {"barcode": "17982694578", "amount": 5}, {"barcode": "90960677255", "amount": 9}, {"barcode": "38114229805", "amount": 2}, {"barcode": "38487530580", "amount": 5}, {"barcode": "25592792120", "amount": 6}, {"barcode": "19052289140", "amount": 6}, {"barcode": "32456274424", "amount": 4}, {"barcode": "97430765105", "amount": 7}, {"barcode": "37819682818", "amount": 6}, {"barcode": "59467066521", "amount": 5}, {"barcode": "85523881684", "amount": 5}, {"barcode": "47626897318", "amount": 8}, {"barcode": "96630359483", "amount": 4}, {"barcode": "79973166341", "amount": 7}, {"barcode": "13716007213", "amount": 10}, {"barcode": "61927747637", "amount": 6}, {"barcode": "87926492738", "amount": 6}, {"barcode": "47307672586", "amount": 7}, {"barcode": "54679531275", "amount": 4}, {"barcode": "20315114794", "amount": 8}, {"barcode": "66265085588", "amount": 3}, {"barcode": "44471149041", "amount": 6}, {"barcode": "16056551319", "amount": 5}, {"barcode": "55775106858", "amount": 5}, {"barcode": "38148160252", "amount": 8}, {"barcode": "19835023632", "amount": 8}, {"barcode": "68496574809", "amount": 2}, {"barcode": "20841391096", "amount": 2}, {"barcode": "65861764049", "amount": 5}, {"barcode": "21958197776", "amount": 3}, {"barcode": "52357621429", "amount": 1}, {"barcode": "98833107102", "amount": 5}, {"barcode": "38971324467", "amount": 4}, {"barcode": "90134864677", "amount": 3}, {"barcode": "99678572251", "amount": 9}, {"barcode": "14523563214", "amount": 1}, {"barcode": "52739049168", "amount": 9}, {"barcode": "19443438871", "amount": 9}, {"barcode": "72187332248", "amount": 3}, {"barcode": "38334777459", "amount": 9}]}]}